wadllib/__init__.py
wadllib/application.py
wadllib/iso_strptime.py
wadllib/docs/CONTRIBUTING.rst
wadllib/docs/Makefile
wadllib/docs/NEWS.rst
wadllib/docs/conf.py
wadllib/docs/index.rst
wadllib/docs/main.rst
wadllib/tests/__init__.py
wadllib/tests/test_docs.py
wadllib/tests/data/__init__.py
wadllib/tests/data/data-types-wadl.xml
wadllib/tests/data/launchpad-wadl.xml
wadllib/tests/data/links-wadl.xml
wadllib/tests/data/multipart-binary-wadl.xml
wadllib/tests/data/options-wadl.xml
wadllib/tests/data/person-limi.json
wadllib/tests/data/personset-page2.json
wadllib/tests/data/personset.json
wadllib/tests/data/root.json
wadllib-2.0.0.dist-info/COPYING.txt
wadllib-2.0.0.dist-info/METADATA
wadllib-2.0.0.dist-info/WHEEL
wadllib-2.0.0.dist-info/top_level.txt
wadllib-2.0.0.dist-info/RECORD
