Metadata-Version: 2.1
Name: wadllib
Version: 2.0.0
Summary: Navigate HTTP resources using WADL files as guides.
Home-page: https://launchpad.net/wadllib
Download-URL: https://launchpad.net/wadllib/+download
Maintainer: LAZR Developers
Maintainer-email: lazr-developers@lists.launchpad.net
License: LGPL v3
Project-URL: Source, https://code.launchpad.net/wadllib
Project-URL: Issue Tracker, https://bugs.launchpad.net/wadllib
Project-URL: Documentation, https://wadllib.readthedocs.io/en/latest/
Classifier: Development Status :: 5 - Production/Stable
Classifier: Intended Audience :: Developers
Classifier: License :: OSI Approved :: GNU Library or Lesser General Public License (LGPL)
Classifier: Operating System :: OS Independent
Classifier: Programming Language :: Python
Classifier: Programming Language :: Python :: 3
Classifier: Programming Language :: Python :: 3.8
Classifier: Programming Language :: Python :: 3.9
Classifier: Programming Language :: Python :: 3.10
Classifier: Programming Language :: Python :: 3.11
Classifier: Programming Language :: Python :: 3.12
Classifier: Programming Language :: Python :: 3.13
Requires-Python: >=3.8
License-File: COPYING.txt
Requires-Dist: importlib-resources; python_version < "3.9"
Requires-Dist: lazr.uri
Provides-Extra: docs
Requires-Dist: Sphinx; extra == "docs"
Provides-Extra: test
Requires-Dist: multipart; extra == "test"
